deployml/__init__.py
deployml/core/__init__.py
deployml/keras/__init__.py
deployml/keras/deploy/__init__.py
deployml/keras/models/__init__.py
deployml/keras/models/neural_network.py
deployml/keras/train/__init__.py
deployml/keras/train/training.py
deployml/sklearn/__init__.py
deployml/sklearn/deploy/__init__.py
deployml/sklearn/deploy/base.py
deployml/sklearn/models/__init__.py
deployml/sklearn/models/decision_tree.py
deployml/sklearn/models/import.py
deployml/sklearn/models/logistic_regression.py
deployml/sklearn/models/neural_network.py
deployml/sklearn/models/support_vector.py
deployml/sklearn/train/__init__.py
deployml/sklearn/train/training.py
deployml/tensorflow/__init__.py
deployml/tensorflow/deploy/__init__.py
deployml/tensorflow/models/__init__.py
deployml/tensorflow/train/__init__.py
deployml-0.0.1.dist-info/METADATA
deployml-0.0.1.dist-info/RECORD
deployml-0.0.1.dist-info/WHEEL
deployml-0.0.1.dist-info/top_level.txt
