Metadata-Version: 2.1
Name: deployml
Version: 0.0.1
Summary: Easy training and deployment of machine learning algorithms
Home-page: https://github.com/deploy-ml/deploy-ml
Author: Maxwell Flitton, Romain Belia
Author-email: maxwellflitton@gmail.com
License: UNKNOWN
Platform: UNKNOWN
Classifier: Programming Language :: Python :: 3
Classifier: License :: OSI Approved :: MIT License
Classifier: Operating System :: OS Independent
Classifier: Development Status :: 1 - Planning
Classifier: Topic :: Scientific/Engineering :: Information Analysis
Classifier: Topic :: Software Development :: Build Tools
Requires-Dist: pandas
Requires-Dist: imblearn
Requires-Dist: sklearn
Requires-Dist: numpy
Requires-Dist: matplotlib
